COPYING
MANIFEST.in
README.rst
TODO.txt
setup.py
tallywallet/common/__init__.py
tallywallet/common/currency.py
tallywallet/common/debunking.py
tallywallet/common/exchange.py
tallywallet/common/finance.py
tallywallet/common/ledger.py
tallywallet/common/output.py
tallywallet/common/trade.py
tallywallet/common/doc/api.rst
tallywallet/common/doc/finance.rst
tallywallet/common/doc/index.rst
tallywallet/common/doc/selinger.rst
tallywallet/common/doc/wilson.rst
tallywallet/common/doc/html/api.html
tallywallet/common/doc/html/finance.html
tallywallet/common/doc/html/genindex.html
tallywallet/common/doc/html/index.html
tallywallet/common/doc/html/py-modindex.html
tallywallet/common/doc/html/search.html
tallywallet/common/doc/html/searchindex.js
tallywallet/common/doc/html/selinger.html
tallywallet/common/doc/html/wilson.html
tallywallet/common/doc/html/_sources/api.rst.txt
tallywallet/common/doc/html/_sources/finance.rst.txt
tallywallet/common/doc/html/_sources/index.rst.txt
tallywallet/common/doc/html/_sources/selinger.rst.txt
tallywallet/common/doc/html/_sources/wilson.rst.txt
tallywallet/common/doc/html/_static/basic.css
tallywallet/common/doc/html/_static/doctools.js
tallywallet/common/doc/html/_static/documentation_options.js
tallywallet/common/doc/html/_static/file.png
tallywallet/common/doc/html/_static/jquery-3.4.1.js
tallywallet/common/doc/html/_static/jquery.js
tallywallet/common/doc/html/_static/language_data.js
tallywallet/common/doc/html/_static/minus.png
tallywallet/common/doc/html/_static/plus.png
tallywallet/common/doc/html/_static/pygments.css
tallywallet/common/doc/html/_static/searchtools.js
tallywallet/common/doc/html/_static/underscore-1.3.1.js
tallywallet/common/doc/html/_static/underscore.js
tallywallet/common/doc/html/_static/css/badge_only.css
tallywallet/common/doc/html/_static/css/theme.css
tallywallet/common/doc/html/_static/js/modernizr.min.js
tallywallet/common/doc/html/_static/js/theme.js
tallywallet/common/test/__init__.py
tallywallet_common.egg-info/PKG-INFO
tallywallet_common.egg-info/SOURCES.txt
tallywallet_common.egg-info/dependency_links.txt
tallywallet_common.egg-info/entry_points.txt
tallywallet_common.egg-info/namespace_packages.txt
tallywallet_common.egg-info/not-zip-safe
tallywallet_common.egg-info/requires.txt
tallywallet_common.egg-info/top_level.txt