Metadata-Version: 2.1
Name: tallywallet-common
Version: 0.10.0
Summary: A currency trading ledger in Python
Home-page: https://www.assembla.com/spaces/tallywallet/messages
Author: D Haynes
Author-email: tundish@thuswise.org
License: UNKNOWN
Platform: UNKNOWN
Classifier: Operating System :: OS Independent
Classifier: Programming Language :: Python :: 3.4
Classifier: License :: OSI Approved :: GNU Affero General Public License v3 or later (AGPLv3+)
Provides-Extra: test
Provides-Extra: docbuild
Provides-Extra: dev
